{
  "userinfo": [
    {
      "id": "69e2",
      "email": "sagat56780@gmail.com",
      "name": "Sagar Kumar",
      "phone": "843029662"
    },
    {
      "id": "87bb",
      "email": "sagat56780@gmail.com",
      "name": "Sagar Kumar",
      "phone": "843029662"
    },
    {
      "id": "b284",
      "email": "sagat56780@gmail.com",
      "name": "Sagar Kumar",
      "phone": "843029662"
    },
    {
      "id": "c9cb",
      "email": "sagat56780@gmail.com",
      "name": "Sagar Kumar",
      "phone": "843029662"
    },
    {
      "id": "132c",
      "email": "sagat56780@gmail.com",
      "name": "Sagar Kumar",
      "phone": "843029662"
    },
    {
      "id": "a2b4",
      "email": "sagat56780@gmail.com",
      "name": "Sagar Kumar",
      "phone": "843029662"
    },
    {
      "id": "cf9d",
      "email": "sagat56780@gmail.com",
      "name": "Sagar Kumar",
      "phone": "843029662"
    },
    {
      "id": "1696",
      "email": "sagat56780@gmail.com",
      "name": "Sagar Kumar",
      "phone": "843029662"
    },
    {
      "id": "8203",
      "email": "sagat56780@gmail.com",
      "name": "Sagar Kumar",
      "phone": "843029662"
    },
    {
      "id": "a4b8",
      "email": "sagat56780@gmail.com",
      "name": "Sagar Kumar",
      "phone": "843029662"
    },
    {
      "id": "85d3",
      "email": "sagat56780@gmail.com",
      "name": "Sagar Kumar",
      "phone": "843029662"
    },
    {
      "id": "f5f9",
      "email": "sagat56780@gmail.com",
      "name": "Sagar Kumar",
      "phone": "843029662"
    },
    {
      "id": "b333",
      "email": "sagat56780@gmail.com",
      "name": "Sagar Kumar",
      "phone": "843029662"
    },
    {
      "id": "928a",
      "email": "sagat56780@gmail.com",
      "name": "Sagar Kumar",
      "phone": "843029662"
    },
    {
      "id": "e77c",
      "email": "sagat56780@gmail.com",
      "name": "Sagar Kumar",
      "phone": "843029662"
    },
    {
      "id": "a21d",
      "email": "sagat56780@gmail.com",
      "name": "Sagar Kumar",
      "phone": "843029662"
    },
    {
      "id": "69a7",
      "email": "sagat56780@gmail.com",
      "name": "Sagar Kumar",
      "phone": "843029662"
    },
    {
      "id": "592e",
      "email": "sagat56780@gmail.com",
      "name": "Sagar Kumar",
      "phone": "843029662"
    },
    {
      "id": "8e2e",
      "email": "sagat56780@gmail.com",
      "name": "Sagar Kumar",
      "phone": "843029662"
    },
    {
      "id": "3e6a",
      "email": "sagat56780@gmail.com",
      "name": "Sagar Kumar",
      "phone": "843029662"
    },
    {
      "id": "717a",
      "email": "sagat56780@gmail.com",
      "name": "Sagar Kumar",
      "phone": "843029662"
    },
    {
      "id": "ef5a",
      "email": "sagat56780@gmail.com",
      "name": "Sagar Kumar",
      "phone": "843029662"
    },
    {
      "id": "b5df",
      "email": "sagat56780@gmail.com",
      "name": "Sagar Kumar",
      "phone": "843029662"
    },
    {
      "id": "f7f4",
      "email": "sagat56780@gmail.com",
      "name": "Sagar Kumar",
      "phone": "843029662"
    },
    {
      "id": "7f39",
      "email": "sagat56780@gmail.com",
      "name": "Sagar Kumar",
      "phone": "843029662"
    },
    {
      "id": "c703",
      "email": "sagat56780@gmail.com",
      "name": "Sagar Kumar",
      "phone": "843029662"
    },
    {
      "id": "117d",
      "email": "sagat56780@gmail.com",
      "name": "Sagar Kumar",
      "phone": "843029662"
    },
    {
      "id": "2c2f",
      "email": "sagat56780@gmail.com",
      "name": "Sagar Kumar",
      "phone": "843029662"
    },
    {
      "id": "7899",
      "email": "sagat56780@gmail.com",
      "name": "Sagar Kumar",
      "phone": "843029662"
    },
    {
      "id": "77e2",
      "email": "sagat56780@gmail.com",
      "name": "Sagar Kumar",
      "phone": "843029662"
    },
    {
      "id": "112e",
      "email": "sagat56780@gmail.com",
      "name": "Sagar Kumar",
      "phone": "843029662"
    },
    {
      "id": "9a2c",
      "email": "sagat56780@gmail.com",
      "name": "Sagar Kumar",
      "phone": "08430296626"
    },
    {
      "id": "2def",
      "email": "sagat56780@gmail.com",
      "name": "Sagar Kumar",
      "phone": "08430296626"
    },
    {
      "id": "9358",
      "email": "sagat56780@gmail.com",
      "name": "Sagar Kumar",
      "phone": "843029662"
    },
    {
      "id": "a20e",
      "email": "sagat56780@gmail.com",
      "name": "Sagar Kumar",
      "phone": "08430296626"
    },
    {
      "id": "db82",
      "email": "sagat56780@gmail.com",
      "name": "Sagar Kumar",
      "phone": "843029662"
    },
    {
      "id": "ed0c",
      "email": "sagat56780@gmail.com",
      "name": "Sagar Kumar",
      "phone": "843029662"
    },
    {
      "id": "241b",
      "email": "sagat56780@gmail.com",
      "name": "Sagar Kumar",
      "phone": "843029662"
    },
    {
      "id": "b1e4",
      "email": "sagat56780@gmail.com",
      "name": "Sagar Kumar",
      "phone": "843029662"
    },
    {
      "id": "204c",
      "email": "sagat56780@gmail.com",
      "name": "Sagar Kumar",
      "phone": "843029662"
    },
    {
      "id": "7e85",
      "email": "sagat56780@gmail.com",
      "name": "Sagar Kumar",
      "phone": "843029662"
    },
    {
      "id": "8c2b",
      "email": "sagat56780@gmail.com",
      "name": "Sagar Kumar",
      "phone": "843029662"
    },
    {
      "id": "a9c8",
      "email": "sagat56780@gmail.com",
      "name": "Sagar Kumar",
      "phone": "843029662"
    },
    {
      "id": "aee8",
      "email": "sagat56780@gmail.com",
      "name": "Sagar Kumar",
      "phone": "843029662"
    },
    {
      "id": "1bfc",
      "email": "sagat56780@gmail.com",
      "name": "Sagar Kumar",
      "phone": "843029662"
    },
    {
      "id": "06d8",
      "email": "sagat56780@gmail.com",
      "name": "Sagar Kumar",
      "phone": "843029662"
    },
    {
      "id": "3b79",
      "email": "sagat56780@gmail.com",
      "name": "Sagar Kumar",
      "phone": "843029662"
    },
    {
      "id": "dce4",
      "email": "sagat56780@gmail.com",
      "name": "Sagar Kumar",
      "phone": "08430296626"
    },
    {
      "id": "3dd3",
      "email": "sagat56780@gmail.com",
      "name": "Sagar Kumar",
      "phone": "843029662"
    },
    {
      "id": "bcdc",
      "email": "sagat56780@gmail.com",
      "name": "Sagar Kumar",
      "phone": "843029662"
    },
    {
      "id": "36c1",
      "email": "sagat56780@gmail.com",
      "name": "Sagar Kumar",
      "phone": "843029662"
    }
  ]
}